spelcheck.py
spelcheck-0.3.1.dist-info/WHEEL
spelcheck-0.3.1.dist-info/METADATA
spelcheck-0.3.1.dist-info/RECORD
