Metadata-Version: 2.1
Name: spelcheck
Version: 0.3.1
Summary: Automagically spellcheck your classes
Author: L3viathan
Author-email: git@l3vi.de
Requires-Python: >=3.7,<4.0
Classifier: Programming Language :: Python :: 3
Classifier: Programming Language :: Python :: 3.7
Classifier: Programming Language :: Python :: 3.8
Requires-Dist: fuzzywuzzy (>=0.18.0,<0.19.0)
